<annotation>
	<folder>Unusual</folder>
	<filename>25.jpg</filename>
	<path>F:\Dataset\Unusual\25.jpg</path>
	<source>
		<database>Unknown</database>
	</source>
	<size>
		<width>1023</width>
		<height>681</height>
		<depth>3</depth>
	</size>
	<segmented>0</segmented>
	<object>
		<name>fight</name>
		<pose>Unspecified</pose>
		<truncated>0</truncated>
		<difficult>0</difficult>
		<bndbox>
			<xmin>148</xmin>
			<ymin>32</ymin>
			<xmax>816</xmax>
			<ymax>605</ymax>
		</bndbox>
	</object>
</annotation>
