<annotation>
	<folder>Unusual</folder>
	<filename>38.jpg</filename>
	<path>F:\Dataset\Unusual\38.jpg</path>
	<source>
		<database>Unknown</database>
	</source>
	<size>
		<width>612</width>
		<height>408</height>
		<depth>3</depth>
	</size>
	<segmented>0</segmented>
	<object>
		<name>fall</name>
		<pose>Unspecified</pose>
		<truncated>0</truncated>
		<difficult>0</difficult>
		<bndbox>
			<xmin>137</xmin>
			<ymin>79</ymin>
			<xmax>562</xmax>
			<ymax>389</ymax>
		</bndbox>
	</object>
</annotation>
